odoo/addons/hr_attendance_mitxelena/__init__.py
odoo/addons/hr_attendance_mitxelena/__manifest__.py
odoo/addons/hr_attendance_mitxelena/data/assets.xml
odoo/addons/hr_attendance_mitxelena/data/hr_attendance_scheduled_action.xml
odoo/addons/hr_attendance_mitxelena/data/hr_attendance_server_action.xml
odoo/addons/hr_attendance_mitxelena/data/hr_attendance_system_parameters.xml
odoo/addons/hr_attendance_mitxelena/data/hr_validation_cron.xml
odoo/addons/hr_attendance_mitxelena/data/resource_calendar_attendances_data.xml
odoo/addons/hr_attendance_mitxelena/data/resource_calendar_cron.xml
odoo/addons/hr_attendance_mitxelena/data/resource_calendar_data.xml
odoo/addons/hr_attendance_mitxelena/helpers/__init__.py
odoo/addons/hr_attendance_mitxelena/helpers/calendar.py
odoo/addons/hr_attendance_mitxelena/i18n/es.po
odoo/addons/hr_attendance_mitxelena/i18n/eu_ES.po
odoo/addons/hr_attendance_mitxelena/i18n/hr_attendance_mitxelena.pot
odoo/addons/hr_attendance_mitxelena/models/__init__.py
odoo/addons/hr_attendance_mitxelena/models/hr_attendance_mitxelena.py
odoo/addons/hr_attendance_mitxelena/models/hr_attendance_validation_sheet.py
odoo/addons/hr_attendance_mitxelena/models/hr_employee.py
odoo/addons/hr_attendance_mitxelena/models/hr_leave_allocation.py
odoo/addons/hr_attendance_mitxelena/models/override.py
odoo/addons/hr_attendance_mitxelena/models/resource_calendar.py
odoo/addons/hr_attendance_mitxelena/readme/USAGE.rst
odoo/addons/hr_attendance_mitxelena/reports/__init__.py
odoo/addons/hr_attendance_mitxelena/reports/attendance_report_template.xml
odoo/addons/hr_attendance_mitxelena/reports/hr_attendance_validation_report.py
odoo/addons/hr_attendance_mitxelena/reports/hr_attendance_validation_report.xml
odoo/addons/hr_attendance_mitxelena/reports/hr_attendance_validation_report_sub_templates.xml
odoo/addons/hr_attendance_mitxelena/reports/hr_attendance_validation_report_template.xml
odoo/addons/hr_attendance_mitxelena/reports/hr_leave_report.py
odoo14_addon_hr_attendance_mitxelena-14.0.1.0.56.dist-info/METADATA
odoo14_addon_hr_attendance_mitxelena-14.0.1.0.56.dist-info/WHEEL
odoo14_addon_hr_attendance_mitxelena-14.0.1.0.56.dist-info/top_level.txt
odoo14_addon_hr_attendance_mitxelena-14.0.1.0.56.dist-info/RECORD
